terminally/__init__.py
terminally/ally.py
terminally-0.1.6.dist-info/METADATA
terminally-0.1.6.dist-info/WHEEL
terminally-0.1.6.dist-info/entry_points.txt
terminally-0.1.6.dist-info/top_level.txt
terminally-0.1.6.dist-info/RECORD
