Metadata-Version: 2.1
Name: terminally
Version: 0.1.6
Requires-Dist: appdirs
Requires-Dist: openai
